devdox_ai_locust/__init__.py
devdox_ai_locust/cli.py
devdox_ai_locust/config.py
devdox_ai_locust/hybrid_loctus_generator.py
devdox_ai_locust/locust_generator.py
devdox_ai_locust/py.typed
devdox_ai_locust/prompt/base_workflow.j2
devdox_ai_locust/prompt/domain.j2
devdox_ai_locust/prompt/locust.j2
devdox_ai_locust/prompt/test_data.j2
devdox_ai_locust/prompt/validation.j2
devdox_ai_locust/prompt/workflow.j2
devdox_ai_locust/schemas/__init__.py
devdox_ai_locust/schemas/processing_result.py
devdox_ai_locust/templates/base_workflow.py.j2
devdox_ai_locust/templates/config.py.j2
devdox_ai_locust/templates/custom_flows.py.j2
devdox_ai_locust/templates/endpoint_template.py.j2
devdox_ai_locust/templates/env.example.j2
devdox_ai_locust/templates/fallback_locust.py.j2
devdox_ai_locust/templates/locust.py.j2
devdox_ai_locust/templates/readme.md.j2
devdox_ai_locust/templates/requirement.txt.j2
devdox_ai_locust/templates/test_data.py.j2
devdox_ai_locust/templates/user_classes.py.j2
devdox_ai_locust/templates/utils.py.j2
devdox_ai_locust/templates/mongo/data_provider.py.j2
devdox_ai_locust/templates/mongo/db_config.py.j2
devdox_ai_locust/templates/mongo/db_integration.j2
devdox_ai_locust/utils/__init__.py
devdox_ai_locust/utils/file_creation.py
devdox_ai_locust/utils/open_ai_parser.py
devdox_ai_locust/utils/swagger_utils.py
devdox_ai_locust-0.1.9.dist-info/licenses/LICENSE
devdox_ai_locust-0.1.9.dist-info/METADATA
devdox_ai_locust-0.1.9.dist-info/WHEEL
devdox_ai_locust-0.1.9.dist-info/entry_points.txt
devdox_ai_locust-0.1.9.dist-info/top_level.txt
devdox_ai_locust-0.1.9.dist-info/RECORD
