Metadata-Version: 2.4
Name: devdox_ai_locust
Version: 0.1.9
Summary: AI-powered Locust load test generator from API documentation
Author-email: Hayat Bourji <hayat.bourgi@montyholding.com>
Maintainer-email: Hayat Bourji <hayat.bourgi@montyholding.com>
License: Apache-2.0
Project-URL: Homepage, https://github.com/montymobile1/devdox-ai-locust
Project-URL: Repository, https://github.com/montymobile1/devdox-ai-locust
Keywords: locust,load-testing,api,testing,performance,ai,openapi,swagger
Classifier: Development Status :: 3 - Alpha
Classifier: Intended Audience :: Developers
Classifier: License :: OSI Approved :: Apache Software License
Classifier: Operating System :: OS Independent
Classifier: Programming Language :: Python :: 3
Classifier: Programming Language :: Python :: 3.12
Classifier: Topic :: Software Development :: Testing
Classifier: Topic :: Software Development :: Quality Assurance
Classifier: Topic :: Internet :: WWW/HTTP :: HTTP Servers
Classifier: Topic :: System :: Networking :: Monitoring
Requires-Python: >=3.12
License-File: LICENSE
Requires-Dist: click>=8.0.0
Requires-Dist: pyyaml>=6.0
Requires-Dist: requests>=2.28.0
Requires-Dist: locust>=2.0.0
Requires-Dist: faker>=15.0.0
Requires-Dist: colorama>=0.4.0
Requires-Dist: rich>=12.0.0
Requires-Dist: pydantic>=1.10.0
Requires-Dist: langchain-together==0.3.0
Requires-Dist: together==1.5.17
Requires-Dist: jinja2>=3.0.0
Requires-Dist: black==25.1.0
Requires-Dist: pydantic-settings==2.10.1
Provides-Extra: dev
Requires-Dist: pytest>=7.0; extra == "dev"
Requires-Dist: pytest-cov>=4.0; extra == "dev"
Requires-Dist: black>=22.0; extra == "dev"
Requires-Dist: flake8>=5.0; extra == "dev"
Requires-Dist: mypy>=1.0; extra == "dev"
Requires-Dist: pre-commit>=2.20; extra == "dev"
Requires-Dist: twine>=4.0; extra == "dev"
Requires-Dist: build>=0.8; extra == "dev"
Requires-Dist: ruff==0.13.1; extra == "dev"
Requires-Dist: types-Pygments==2.19.0.20250809; extra == "dev"
Provides-Extra: docs
Requires-Dist: sphinx>=5.0; extra == "docs"
Requires-Dist: sphinx-rtd-theme>=1.0; extra == "docs"
Requires-Dist: myst-parser>=0.18; extra == "docs"
Provides-Extra: test
Requires-Dist: pytest>=7.0; extra == "test"
Requires-Dist: pytest-cov>=4.0; extra == "test"
Requires-Dist: pytest-mock>=3.8; extra == "test"
Requires-Dist: pytest-asyncio>=0.21; extra == "test"
Requires-Dist: httpx>=0.23; extra == "test"
Requires-Dist: aiofiles>=23.0; extra == "test"
Requires-Dist: coverage>=7.0; extra == "test"
Provides-Extra: ai
Requires-Dist: openai>=0.27.0; extra == "ai"
Requires-Dist: anthropic>=0.3.0; extra == "ai"
Dynamic: license-file
